{"data_de_validade_do_rca": "Sem rca", "data_da_compra_ou_transferencia": "160310", "categoria_de_registro": "PRIVADA SERVICO AEREO PRIVADOS", "peso_maximo_de_decolagem": "16375 - Kg", "operador": "CIA.DE TEC.NORTE DE MINAS-COTEMINAS", "numero_de_serie": "7500234", "numero_dos_certificados__cm___ca": "16646", "tipo_icao": "C750", "fabricante": "CESSNA AIRCRAFT", "classe_da_aeronave": "POUSO CONVECIONAL 2 MOTORES JATO/TURBOFAN", "situacao_no_rab": "", "numero_maximo_de_passageiros": "009", "cpf_ou_cgc_prop": "", "cpf_ou_cgc_oper": "22677520000176", "data_de_validade_do_ca": "03/02/17", "tipo_de_habilitacao_para_pilotos": "C750", "matricula": "PPAAA", "motivo_s": "", "situacao_de_aeronavegabilidade": "MATRICULA CANCELADA ", "modelo": "750", "proprietario": "WELLS FARGO BANK NORTHWEST NAT.ASSOC"}
{"peso_maximo_de_decolagem": "1406 - Kg", "situacao_no_rab": "", "cpf_ou_cgc_prop": "16902661987", "matricula": "PPAAC", "motivo_s": "", "numero_dos_certificados__cm___ca": "21795", "classe_da_aeronave": "POUSO CONVECIONAL 1 MOTOR CONVENCIONAL", "situacao_de_aeronavegabilidade": "Normal", "data_de_validade_do_ca": "07/05/19", "numero_de_serie": "R18200851", "tipo_icao": "C82R", "data_de_validade_do_rca": "Sem rca", "cpf_ou_cgc_oper": "16902661987", "tipo_de_habilitacao_para_pilotos": "MNTE", "categoria_de_registro": "PRIVADA SERVICO AEREO PRIVADOS", "operador": "LIRIO PEDRO RIGON", "fabricante": "CESSNA AIRCRAFT", "data_da_compra_ou_transferencia": "030516", "numero_maximo_de_passageiros": "003", "modelo": "R182", "data_de_validade_da_iam": "040817", "proprietario": "LIRIO PEDRO RIGON"}
{"peso_maximo_de_decolagem": "13744 - Kg", "situacao_no_rab": "", "cpf_ou_cgc_prop": "33655721000199", "matricula": "PPAAD", "motivo_s": "", "numero_dos_certificados__cm___ca": "18166", "classe_da_aeronave": "POUSO CONVECIONAL 2 MOTORES JATO/TURBOFAN", "situacao_de_aeronavegabilidade": "Normal", "data_de_validade_do_ca": "21/01/21", "numero_de_serie": "680-0260", "tipo_icao": "C680", "data_de_validade_do_rca": "Sem rca", "cpf_ou_cgc_oper": "33655721000199", "tipo_de_habilitacao_para_pilotos": "C680", "categoria_de_registro": "PRIVADA SERVICO AEREO PRIVADOS", "operador": "CONFEDERACAO BRASILEIRA DE FUTEBOL", "fabricante": "CESSNA AIRCRAFT", "data_da_compra_ou_transferencia": "050309", "numero_maximo_de_passageiros": "009", "modelo": "680", "data_de_validade_da_iam": "040817", "proprietario": "CONFEDERACAO BRASILEIRA DE FUTEBOL"}
{"peso_maximo_de_decolagem": "1088 - Kg", "situacao_no_rab": "ARROLAMENTOS BENS REC.FED./INDISPONIVEL", "cpf_ou_cgc_prop": "13013997000166", "matricula": "PPAAE", "motivo_s": "", "numero_dos_certificados__cm___ca": "18647", "classe_da_aeronave": "HELICOPTERO 1 MOTOR CONVENCIONAL", "situacao_de_aeronavegabilidade": "Normal", "data_de_validade_do_ca": "15/03/17", "numero_de_serie": "1996", "tipo_icao": "R44", "data_de_validade_do_rca": "Sem rca", "cpf_ou_cgc_oper": "13013997000166", "tipo_de_habilitacao_para_pilotos": "HMNC", "categoria_de_registro": "MULTIPLA CATEGORIA TPX/SAE-AC/F/P/R (OBS.COD.CA = 23)", "operador": "HELICON TAXI AEREO LTDA", "fabricante": "ROBINSON HELICOPTER", "data_da_compra_ou_transferencia": "291210", "numero_maximo_de_passageiros": "003", "modelo": "R44", "data_de_validade_da_iam": "150117", "proprietario": "HELICON TAXI AEREO LTDA"}
{"peso_maximo_de_decolagem": "19142 - Kg", "situacao_no_rab": "ARRENDAMENTO OPERACIONAL", "cpf_ou_cgc_prop": "", "matricula": "PPAAF", "motivo_s": "", "numero_dos_certificados__cm___ca": "16348", "classe_da_aeronave": "POUSO CONVECIONAL 2 MOTORES JATO/TURBOFAN", "situacao_de_aeronavegabilidade": "MATRICULA CANCELADA ", "data_de_validade_do_ca": "05/09/15", "numero_de_serie": "016", "tipo_icao": "F2TH", "data_de_validade_do_rca": "Sem rca", "cpf_ou_cgc_oper": "58725102000154", "tipo_de_habilitacao_para_pilotos": "FA2E", "categoria_de_registro": "PRIVADA SERV.TRANSP.AEREO PUBLICO NAO REGULAR TX.AEREO", "operador": "METRO TAXI AEREO LTDA", "fabricante": "DASSAULT AVIATION", "data_da_compra_ou_transferencia": "191103", "numero_maximo_de_passageiros": "009", "modelo": "FALCON 2000EX", "data_de_validade_da_iam": "070814", "proprietario": "CITICORP LEASING INTERNATIONAL, INC"}
{"peso_maximo_de_decolagem": "1633 - Kg", "situacao_no_rab": "ARRENDAMENTO OPERACIONAL/ALIENACAO FIDUCIARIA", "cpf_ou_cgc_prop": "03017677000120", "matricula": "PPAAG", "motivo_s": "Situa\u00e7\u00e3o irregular no RAB", "numero_dos_certificados__cm___ca": "19040", "classe_da_aeronave": "POUSO CONVECIONAL 1 MOTOR CONVENCIONAL", "situacao_de_aeronavegabilidade": " CERTIFICADO DE AERONAVEGABILIDADE (CA) SUSPENSO", "data_de_validade_do_ca": "27/06/22", "numero_de_serie": "T20608735", "tipo_icao": "C206", "data_de_validade_do_rca": "Sem rca", "cpf_ou_cgc_oper": "38737965972", "tipo_de_habilitacao_para_pilotos": "MNTE", "categoria_de_registro": "PRIVADA SERVICO AEREO PRIVADOS", "operador": "LUIZ ALBERTO VIOLATO", "fabricante": "CESSNA AIRCRAFT", "data_da_compra_ou_transferencia": "", "numero_maximo_de_passageiros": "005", "modelo": "T206H", "data_de_validade_da_iam": "270617", "proprietario": "BANCO J SAFRA S.A"}
{"peso_maximo_de_decolagem": "1633 - Kg", "situacao_no_rab": "", "cpf_ou_cgc_prop": "23673867000103", "matricula": "PPAAJ", "motivo_s": "", "numero_dos_certificados__cm___ca": "22013", "classe_da_aeronave": "POUSO CONVECIONAL 1 MOTOR CONVENCIONAL", "situacao_de_aeronavegabilidade": "Normal", "data_de_validade_do_ca": "20/08/19", "numero_de_serie": "3966", "tipo_icao": "SR22", "data_de_validade_do_rca": "Sem rca", "cpf_ou_cgc_oper": "23673867000103", "tipo_de_habilitacao_para_pilotos": "MNTE", "categoria_de_registro": "PRIVADA SERVICO AEREO PRIVADOS", "operador": "ITK LOCADORA DE VEICULOS LTDA", "fabricante": "CIRRUS DESIGN", "data_da_compra_ou_transferencia": "041215", "numero_maximo_de_passageiros": "004", "modelo": "SR22", "data_de_validade_da_iam": "200717", "proprietario": "ITK LOCADORA DE VEICULOS LTDA"}
{"peso_maximo_de_decolagem": "1973 - Kg", "situacao_no_rab": "", "cpf_ou_cgc_prop": "03910415172", "matricula": "PPAAK", "motivo_s": "", "numero_dos_certificados__cm___ca": "23186", "classe_da_aeronave": "POUSO CONVECIONAL 1 MOTOR CONVENCIONAL", "situacao_de_aeronavegabilidade": "CERTIFICADO DE AERONAVEGABILIDADE (CA) VENCIDO", "data_de_validade_do_ca": "", "numero_de_serie": "7861", "tipo_icao": "VALI", "data_de_validade_do_rca": "Sem rca", "cpf_ou_cgc_oper": "03910415172", "tipo_de_habilitacao_para_pilotos": "MNTE", "categoria_de_registro": "PRIVADA HISTORICA", "operador": "JOAO FRANCISCO AMARO", "fabricante": "VULTEE", "data_da_compra_ou_transferencia": "270315", "numero_maximo_de_passageiros": "001", "modelo": "BT-13", "data_de_validade_da_iam": "", "proprietario": "JOAO FRANCISCO AMARO"}
{"peso_maximo_de_decolagem": "1542 - Kg", "situacao_no_rab": "ARRENDAMENTO MERCANTIL", "cpf_ou_cgc_prop": "47509120000182", "matricula": "PPAAL", "motivo_s": "", "numero_dos_certificados__cm___ca": "19237", "classe_da_aeronave": "POUSO CONVECIONAL 1 MOTOR CONVENCIONAL", "situacao_de_aeronavegabilidade": "Normal", "data_de_validade_do_ca": "22/06/22", "numero_de_serie": "3674", "tipo_icao": "SR22", "data_de_validade_do_rca": "Sem rca", "cpf_ou_cgc_oper": "06351305000124", "tipo_de_habilitacao_para_pilotos": "MNTE", "categoria_de_registro": "PRIVADA SERVICO AEREO PRIVADOS", "operador": "AVANT AGROQUIMICA LTDA", "fabricante": "CIRRUS DESIGN", "data_da_compra_ou_transferencia": "041010", "numero_maximo_de_passageiros": "003", "modelo": "SR22", "data_de_validade_da_iam": "220617", "proprietario": "BRADESCO LEASING S.A ARREND.MERCANTIL"}
{"peso_maximo_de_decolagem": "1950 - Kg", "situacao_no_rab": "", "cpf_ou_cgc_prop": "35317426120", "matricula": "PPAAM", "motivo_s": "", "numero_dos_certificados__cm___ca": "18180", "classe_da_aeronave": "POUSO CONVECIONAL 1 MOTOR CONVENCIONAL", "situacao_de_aeronavegabilidade": "CERTIFICADO DE AERONAVEGABILIDADE (CA) CANCELADO", "data_de_validade_do_ca": "27/02/21", "numero_de_serie": "4636457", "tipo_icao": "PA46", "data_de_validade_do_rca": "Sem rca", "cpf_ou_cgc_oper": "35317426120", "tipo_de_habilitacao_para_pilotos": "MNTE", "categoria_de_registro": "PRIVADA SERVICO AEREO PRIVADOS", "operador": "GIOVANI SOARES RAMOS", "fabricante": "PIPER AIRCRAFT", "data_da_compra_ou_transferencia": "311016", "numero_maximo_de_passageiros": "005", "modelo": "PA-46-350P", "data_de_validade_da_iam": "270216", "proprietario": "GIOVANI SOARES RAMOS"}
{"peso_maximo_de_decolagem": "1134 - Kg", "situacao_no_rab": "ARRENDAMENTO OPERACIONAL", "cpf_ou_cgc_prop": "02311117000111", "matricula": "PPAAN", "motivo_s": "", "numero_dos_certificados__cm___ca": "18796", "classe_da_aeronave": "HELICOPTERO 1 MOTOR CONVENCIONAL", "situacao_de_aeronavegabilidade": "Normal", "data_de_validade_do_ca": "16/02/22", "numero_de_serie": "12855", "tipo_icao": "R44", "data_de_validade_do_rca": "Sem rca", "cpf_ou_cgc_oper": "23146151000158", "tipo_de_habilitacao_para_pilotos": "HMNC", "categoria_de_registro": "PRIVADA SERVICO AEREO PRIVADOS", "operador": "M L SOUTO DA SILVA - ME", "fabricante": "ROBINSON HELICOPTER", "data_da_compra_ou_transferencia": "191015", "numero_maximo_de_passageiros": "003", "modelo": "R44 II", "data_de_validade_da_iam": "160217", "proprietario": "PONTUAL SERVICOS DE LOC.E CONSTRUTORA LT"}
{"peso_maximo_de_decolagem": "7394 - Kg", "situacao_no_rab": "ALIENACAO FIDUCIARIA", "cpf_ou_cgc_prop": "28195667000106", "matricula": "PPAAO", "motivo_s": "", "numero_dos_certificados__cm___ca": "22735", "classe_da_aeronave": "POUSO CONVECIONAL 2 MOTORES JATO/TURBOFAN", "situacao_de_aeronavegabilidade": "Normal", "data_de_validade_do_ca": "16/09/20", "numero_de_serie": "RK-565", "tipo_icao": "BE40", "data_de_validade_do_rca": "Sem rca", "cpf_ou_cgc_oper": "19635634000149", "tipo_de_habilitacao_para_pilotos": "BE40", "categoria_de_registro": "PRIVADA SERVICO AEREO PRIVADOS", "operador": "CLAREMONT EMPREEND. E PARTICIPACOES LTDA", "fabricante": "HAWKER BEECHCRAFT", "data_da_compra_ou_transferencia": "110615", "numero_maximo_de_passageiros": "008", "modelo": "400A", "data_de_validade_da_iam": "050817", "proprietario": "BANCO ABC BRASIL S.A"}
{"data_de_validade_do_rca": "Sem rca", "data_da_compra_ou_transferencia": "300904", "categoria_de_registro": "PRIVADA SERVICO AEREO PRIVADOS", "peso_maximo_de_decolagem": "1633 - Kg", "operador": "ARNALDO DE ALMEIDA PRADO NETO", "numero_de_serie": "T20608883", "numero_dos_certificados__cm___ca": "18026", "tipo_icao": "C206", "fabricante": "CESSNA AIRCRAFT", "classe_da_aeronave": "POUSO CONVECIONAL 1 MOTOR CONVENCIONAL", "situacao_no_rab": "", "numero_maximo_de_passageiros": "005", "cpf_ou_cgc_prop": "22077354860", "cpf_ou_cgc_oper": "22077354860", "data_de_validade_do_ca": "25/11/20", "tipo_de_habilitacao_para_pilotos": "MNTE", "matricula": "PPAAP", "motivo_s": "", "situacao_de_aeronavegabilidade": "Normal", "modelo": "T206H", "proprietario": "ARNALDO DE ALMEIDA PRADO NETO"}
{"peso_maximo_de_decolagem": "855 - Kg", "situacao_no_rab": "", "cpf_ou_cgc_prop": "03910415172", "matricula": "PPAAR", "motivo_s": "", "numero_dos_certificados__cm___ca": "21699", "classe_da_aeronave": "POUSO CONVECIONAL 1 MOTOR CONVENCIONAL", "situacao_de_aeronavegabilidade": "Normal", "data_de_validade_do_ca": "20/01/44", "numero_de_serie": "1402", "tipo_icao": "ZZZZ", "data_de_validade_do_rca": "IS/EN/TO", "cpf_ou_cgc_oper": "03910415172", "tipo_de_habilitacao_para_pilotos": "MNTE", "categoria_de_registro": "PRIVADA HISTORICA", "operador": "JOAO FRANCISCO AMARO", "fabricante": "RYAN AERONAUTICAL", "data_da_compra_ou_transferencia": "131212", "numero_maximo_de_passageiros": "001", "modelo": "ST-3KR", "data_de_validade_da_iam": "Sem iam", "proprietario": "JOAO FRANCISCO AMARO"}
